LICENSE.txt
MANIFEST.in
README.rst
pf.py
setup.py
pypf/__init__.py
pypf/chart.py
pypf/instrument.py
pypf/terminal_format.py
pypf.egg-info/PKG-INFO
pypf.egg-info/SOURCES.txt
pypf.egg-info/dependency_links.txt
pypf.egg-info/not-zip-safe
pypf.egg-info/requires.txt
pypf.egg-info/top_level.txt