Metadata-Version: 1.1
Name: pypf
Version: 0.9.6
Summary: Create point and figure charts
Home-page: http://github.com/pviglucci/pypf
Author: Peter Viglucci
Author-email: pviglucci@gmail.com
License: MIT License
Keywords: point figure stock chart
Platform: UNKNOWN
Classifier: Development Status :: 4 - Beta
Classifier: License :: OSI Approved :: MIT License
Classifier: Programming Language :: Python :: 3.6
Classifier: Topic :: Office/Business :: Financial :: Investment
